aiogmb/__init__.py
aiogmb/aiogmb.py
aiogmb-0.0.1.dist-info/AUTHORS.rst
aiogmb-0.0.1.dist-info/LICENSE
aiogmb-0.0.1.dist-info/METADATA
aiogmb-0.0.1.dist-info/WHEEL
aiogmb-0.0.1.dist-info/top_level.txt
aiogmb-0.0.1.dist-info/RECORD
