Metadata-Version: 2.1
Name: aiogmb
Version: 0.0.1
Summary: Async client for google's gmb api
Home-page: https://github.com/krapoed/aiogmb
Author: Dzmitry Sianiuk
Author-email: d.sianiuk@gmail.com
License: MIT license
Keywords: aiogmb
Platform: UNKNOWN
Classifier: Development Status :: 2 - Pre-Alpha
Classifier: Intended Audience :: Developers
Classifier: License :: OSI Approved :: MIT License
Classifier: Natural Language :: English
Classifier: Programming Language :: Python :: 2
Classifier: Programming Language :: Python :: 2.7
Classifier: Programming Language :: Python :: 3
Classifier: Programming Language :: Python :: 3.4
Classifier: Programming Language :: Python :: 3.5
Classifier: Programming Language :: Python :: 3.6
Classifier: Programming Language :: Python :: 3.7
